wearing_glasses/__init__.py
wearing_glasses/cp_fl_model.py
wearing_glasses/helper.py
wearing_glasses/plot_glasses.py
wearing_glasses-0.0.3.dist-info/METADATA
wearing_glasses-0.0.3.dist-info/WHEEL
wearing_glasses-0.0.3.dist-info/entry_points.txt
wearing_glasses-0.0.3.dist-info/top_level.txt
wearing_glasses-0.0.3.dist-info/RECORD
