Metadata-Version: 2.1
Name: wearing-glasses
Version: 0.0.3
Summary: Package for 'wearing glasses'
Home-page: http://www.ai.game.tw
Author: BIG CHENG
Author-email: big_cheng.asus@gmail.com
License: UNKNOWN
Platform: UNKNOWN
Classifier: Programming Language :: Python :: 3
Classifier: License :: OSI Approved :: MIT License
Classifier: Operating System :: OS Independent
Requires-Dist: numpy
Requires-Dist: Pillow
Requires-Dist: dlib
Requires-Dist: click
